_xbcf_cpp_.cpython-37m-darwin.so
xbcausalforest/__init__.py
xbcausalforest/xbcf_cpp_.py
xbcausalforest/xbcf_python.py
xbcausalforest-0.1.3.dist-info/METADATA
xbcausalforest-0.1.3.dist-info/WHEEL
xbcausalforest-0.1.3.dist-info/top_level.txt
xbcausalforest-0.1.3.dist-info/RECORD
