Metadata-Version: 2.1
Name: xbcausalforest
Version: 0.1.3
Summary: Implementation of Accelerated Bayesian Causal Forests
Home-page: UNKNOWN
Author: Jingyu He, Saar Yalov, P. Richard Hahn, Nikolay Krantsevich
Author-email: krantsevich@gmail.com
License: Apache-2.0
Platform: UNKNOWN
Requires-Python: >3.7
Requires-Dist: numpy
